sd_helper/__init__.py
sd_helper/auth.py
sd_helper/cli.py
sd_helper/api/__init__.py
sd_helper/api/llm.py
sd_helper/data/__init__.py
sd_helper/data/collector.py
sd_helper/data/http_logger.py
sd_helper/data/request_template.py
sd_helper/data/runner.py
sd_helper/data/storage.py
sd_helper_cli-0.1.1.dist-info/METADATA
sd_helper_cli-0.1.1.dist-info/WHEEL
sd_helper_cli-0.1.1.dist-info/entry_points.txt
sd_helper_cli-0.1.1.dist-info/RECORD
