Metadata-Version: 2.4
Name: sd-helper-cli
Version: 0.1.1
Summary: CLI tool for Huawei Cloud Service Delivery Engineers
Project-URL: Homepage, https://github.com/xuopoj/sd-helper
Project-URL: Repository, https://github.com/xuopoj/sd-helper
Author-email: Sean <xuopoj@gmail.com>
License: MIT
Keywords: cli,cloud,huawei,llm,modelarts,service-delivery
Classifier: Development Status :: 3 - Alpha
Classifier: Environment :: Console
Classifier: Intended Audience :: Developers
Classifier: License :: OSI Approved :: MIT License
Classifier: Programming Language :: Python :: 3.12
Classifier: Topic :: Utilities
Requires-Python: >=3.10
Requires-Dist: click>=8.1.0
Requires-Dist: httpx>=0.27.0
Requires-Dist: pyyaml>=6.0
